zope.app.generations-5.0-py3.9-nspkg.pth
zope/app/generations/__init__.py
zope/app/generations/configure.zcml
zope/app/generations/ftesting.zcml
zope/app/generations/generations.py
zope/app/generations/interfaces.py
zope/app/generations/subscriber.zcml
zope/app/generations/testing.py
zope/app/generations/utility.py
zope/app/generations/browser/__init__.py
zope/app/generations/browser/configure.zcml
zope/app/generations/browser/managerdetails.pt
zope/app/generations/browser/managerdetails.py
zope/app/generations/browser/managers.pt
zope/app/generations/browser/managers.py
zope/app/generations/browser/tests.py
zope/app/generations/demo/__init__.py
zope/app/generations/demo/evolve1.py
zope/app/generations/demo/evolve2.py
zope/app/generations/demo/evolve3.py
zope/app/generations/demo/install.py
zope.app.generations-5.0.dist-info/LICENSE.txt
zope.app.generations-5.0.dist-info/METADATA
zope.app.generations-5.0.dist-info/WHEEL
zope.app.generations-5.0.dist-info/namespace_packages.txt
zope.app.generations-5.0.dist-info/top_level.txt
zope.app.generations-5.0.dist-info/RECORD
