Metadata-Version: 2.1
Name: zope.app.generations
Version: 5.0
Summary: ZMI UI for zope.generations
Home-page: http://github.com/zopefoundation/zope.app.generations
Author: Zope Foundation and Contributors
Author-email: zope-dev@zope.dev
License: ZPL 2.1
Keywords: zope zmi zodb schema generation
Classifier: Development Status :: 5 - Production/Stable
Classifier: Environment :: Web Environment
Classifier: Intended Audience :: Developers
Classifier: License :: OSI Approved :: Zope Public License
Classifier: Programming Language :: Python
Classifier: Natural Language :: English
Classifier: Operating System :: OS Independent
Classifier: Topic :: Internet :: WWW/HTTP
Classifier: Framework :: Zope :: 3
Classifier: Programming Language :: Python
Classifier: Programming Language :: Python :: 3
Classifier: Programming Language :: Python :: 3.7
Classifier: Programming Language :: Python :: 3.8
Classifier: Programming Language :: Python :: 3.9
Classifier: Programming Language :: Python :: 3.10
Classifier: Programming Language :: Python :: 3.11
Classifier: Programming Language :: Python :: Implementation :: CPython
Classifier: Programming Language :: Python :: Implementation :: PyPy
Requires-Python: >=3.7
License-File: LICENSE.txt
Requires-Dist: docutils
Requires-Dist: setuptools
Requires-Dist: zope.app.publication
Requires-Dist: zope.applicationcontrol
Requires-Dist: zope.generations (>=4.0.0a1)
Requires-Dist: zope.interface
Requires-Dist: zope.processlifetime
Provides-Extra: test
Requires-Dist: ZODB ; extra == 'test'
Requires-Dist: zope.app.appsetup ; extra == 'test'
Requires-Dist: zope.app.basicskin (>=4.0.0) ; extra == 'test'
Requires-Dist: zope.app.publication ; extra == 'test'
Requires-Dist: zope.app.wsgi ; extra == 'test'
Requires-Dist: zope.browsermenu ; extra == 'test'
Requires-Dist: zope.browserpage ; extra == 'test'
Requires-Dist: zope.browserresource ; extra == 'test'
Requires-Dist: zope.container ; extra == 'test'
Requires-Dist: zope.login ; extra == 'test'
Requires-Dist: zope.principalregistry ; extra == 'test'
Requires-Dist: zope.publisher ; extra == 'test'
Requires-Dist: zope.securitypolicy ; extra == 'test'
Requires-Dist: zope.testbrowser (>=5.2) ; extra == 'test'
Requires-Dist: zope.testing ; extra == 'test'
Requires-Dist: zope.testrunner ; extra == 'test'
Requires-Dist: zope.traversing (>=4.1.0) ; extra == 'test'
Requires-Dist: webtest ; extra == 'test'
